LICENSE
MANIFEST.in
README.rst
setup.py
codingsoho_pagination.egg-info/PKG-INFO
codingsoho_pagination.egg-info/SOURCES.txt
codingsoho_pagination.egg-info/dependency_links.txt
codingsoho_pagination.egg-info/requires.txt
codingsoho_pagination.egg-info/top_level.txt
docs/blank.txt
pagination/__init__.py
pagination/middleware.py
pagination/models.py
pagination/paginator.py
pagination/tests.py
pagination/templates/pagination/pagination.html
pagination/templatetags/__init__.py
pagination/templatetags/pagination_tags.py