Metadata-Version: 1.1
Name: codingsoho-pagination
Version: 1.0.9
Summary: codingsoho-pagination is based on django-pagination 1.0.7 which source code stop updating now, The update in this version only for adaption
Home-page: http://www.codingsoho.com/
Author: Horde Chief
Author-email: hordechief@qq.com
License: BSD License
Platform: UNKNOWN
Classifier: Environment :: Web Environment
Classifier: Framework :: Django
Classifier: Framework :: Django :: 1.9
Classifier: Framework :: Django :: 1.11
Classifier: Intended Audience :: Developers
Classifier: License :: OSI Approved :: BSD License
Classifier: Operating System :: OS Independent
Classifier: Programming Language :: Python
Classifier: Programming Language :: Python :: 2
Classifier: Programming Language :: Python :: 2.7
Classifier: Topic :: Internet :: WWW/HTTP
Classifier: Topic :: Internet :: WWW/HTTP :: Dynamic Content
